[
  {
    "run_time": "2025-10-11T15:49:06.329755",
    "target": "C:\\Users\\ASUS\\Downloads",
    "moves": [
      {
        "src": "C:\\Users\\ASUS\\Downloads\\2023-ed-pivot-table.xlsm",
        "dst": "C:\\Users\\ASUS\\Downloads\\2025-03\\2023-ed-pivot-table.xlsm",
        "time": "2025-10-11T15:49:06.195969",
        "dry": false
      },
      {
        "src": "C:\\Users\\ASUS\\Downloads\\5f501e94-8ad9-449c-917e-bdec8910e004 (1).docx",
        "dst": "C:\\Users\\ASUS\\Downloads\\2025-06\\5f501e94-8ad9-449c-917e-bdec8910e004 (1).docx",
        "time": "2025-10-11T15:49:06.197526",
        "dry": false
      },
      {
        "src": "C:\\Users\\ASUS\\Downloads\\5f501e94-8ad9-449c-917e-bdec8910e004.docx",
        "dst": "C:\\Users\\ASUS\\Downloads\\2025-05\\5f501e94-8ad9-449c-917e-bdec8910e004.docx",
        "time": "2025-10-11T15:49:06.198777",
        "dry": false
      },
      {
        "src": "C:\\Users\\ASUS\\Downloads\\7-240704155115-9db2c301 (1).pdf",
        "dst": "C:\\Users\\ASUS\\Downloads\\2025-05\\7-240704155115-9db2c301 (1).pdf",
        "time": "2025-10-11T15:49:06.199535",
        "dry": false
      },
      {
        "src": "C:\\Users\\ASUS\\Downloads\\7-240704155115-9db2c301 (10).pdf",
        "dst": "C:\\Users\\ASUS\\Downloads\\2025-05\\7-240704155115-9db2c301 (10).pdf",
        "time": "2025-10-11T15:49:06.200321",
        "dry": false
      },
      {
        "src": "C:\\Users\\ASUS\\Downloads\\7-240704155115-9db2c301 (11).pdf",
        "dst": "C:\\Users\\ASUS\\Downloads\\2025-05\\7-240704155115-9db2c301 (11).pdf",
        "time": "2025-10-11T15:49:06.200813",
        "dry": false
      },
      {
        "src": "C:\\Users\\ASUS\\Downloads\\7-240704155115-9db2c301 (12).pdf",
        "dst": "C:\\Users\\ASUS\\Downloads\\2025-05\\7-240704155115-9db2c301 (12).pdf",
        "time": "2025-10-11T15:49:06.201385",
        "dry": false
      },
      {
        "src": "C:\\Users\\ASUS\\Downloads\\7-240704155115-9db2c301 (13).pdf",
        "dst": "C:\\Users\\ASUS\\Downloads\\2025-05\\7-240704155115-9db2c301 (13).pdf",
        "time": "2025-10-11T15:49:06.201755",
        "dry": false
      },
      {
        "src": "C:\\Users\\ASUS\\Downloads\\7-240704155115-9db2c301 (14).pdf",
        "dst": "C:\\Users\\ASUS\\Downloads\\2025-05\\7-240704155115-9db2c301 (14).pdf",
        "time": "2025-10-11T15:49:06.202151",
        "dry": false
      },
      {
        "src": "C:\\Users\\ASUS\\Downloads\\7-240704155115-9db2c301 (15).pdf",
        "dst": "C:\\Users\\ASUS\\Downloads\\2025-05\\7-240704155115-9db2c301 (15).pdf",
        "time": "2025-10-11T15:49:06.202550",
        "dry": false
      },
      {
        "src": "C:\\Users\\ASUS\\Downloads\\7-240704155115-9db2c301 (16).pdf",
        "dst": "C:\\Users\\ASUS\\Downloads\\2025-05\\7-240704155115-9db2c301 (16).pdf",
        "time": "2025-10-11T15:49:06.202931",
        "dry": false
      },
      {
        "src": "C:\\Users\\ASUS\\Downloads\\7-240704155115-9db2c301 (17).pdf",
        "dst": "C:\\Users\\ASUS\\Downloads\\2025-05\\7-240704155115-9db2c301 (17).pdf",
        "time": "2025-10-11T15:49:06.203295",
        "dry": false
      },
      {
        "src": "C:\\Users\\ASUS\\Downloads\\7-240704155115-9db2c301 (18).pdf",
        "dst": "C:\\Users\\ASUS\\Downloads\\2025-05\\7-240704155115-9db2c301 (18).pdf",
        "time": "2025-10-11T15:49:06.203649",
        "dry": false
      },
      {
        "src": "C:\\Users\\ASUS\\Downloads\\7-240704155115-9db2c301 (18).pptx",
        "dst": "C:\\Users\\ASUS\\Downloads\\2025-05\\7-240704155115-9db2c301 (18).pptx",
        "time": "2025-10-11T15:49:06.204014",
        "dry": false
      },
      {
        "src": "C:\\Users\\ASUS\\Downloads\\7-240704155115-9db2c301 (19).pdf",
        "dst": "C:\\Users\\ASUS\\Downloads\\2025-05\\7-240704155115-9db2c301 (19).pdf",
        "time": "2025-10-11T15:49:06.204408",
        "dry": false
      },
      {
        "src": "C:\\Users\\ASUS\\Downloads\\7-240704155115-9db2c301 (2).pdf",
        "dst": "C:\\Users\\ASUS\\Downloads\\2025-05\\7-240704155115-9db2c301 (2).pdf",
        "time": "2025-10-11T15:49:06.204782",
        "dry": false
      },
      {
        "src": "C:\\Users\\ASUS\\Downloads\\7-240704155115-9db2c301 (20).pdf",
        "dst": "C:\\Users\\ASUS\\Downloads\\2025-05\\7-240704155115-9db2c301 (20).pdf",
        "time": "2025-10-11T15:49:06.205146",
        "dry": false
      },
      {
        "src": "C:\\Users\\ASUS\\Downloads\\7-240704155115-9db2c301 (3).pdf",
        "dst": "C:\\Users\\ASUS\\Downloads\\2025-05\\7-240704155115-9db2c301 (3).pdf",
        "time": "2025-10-11T15:49:06.205670",
        "dry": false
      },
      {
        "src": "C:\\Users\\ASUS\\Downloads\\7-240704155115-9db2c301 (4).pdf",
        "dst": "C:\\Users\\ASUS\\Downloads\\2025-05\\7-240704155115-9db2c301 (4).pdf",
        "time": "2025-10-11T15:49:06.206692",
        "dry": false
      },
      {
        "src": "C:\\Users\\ASUS\\Downloads\\7-240704155115-9db2c301 (5).pdf",
        "dst": "C:\\Users\\ASUS\\Downloads\\2025-05\\7-240704155115-9db2c301 (5).pdf",
        "time": "2025-10-11T15:49:06.207221",
        "dry": false
      },
      {
        "src": "C:\\Users\\ASUS\\Downloads\\7-240704155115-9db2c301 (6).pdf",
        "dst": "C:\\Users\\ASUS\\Downloads\\2025-05\\7-240704155115-9db2c301 (6).pdf",
        "time": "2025-10-11T15:49:06.208010",
        "dry": false
      },
      {
        "src": "C:\\Users\\ASUS\\Downloads\\7-240704155115-9db2c301 (7).pdf",
        "dst": "C:\\Users\\ASUS\\Downloads\\2025-05\\7-240704155115-9db2c301 (7).pdf",
        "time": "2025-10-11T15:49:06.208509",
        "dry": false
      },
      {
        "src": "C:\\Users\\ASUS\\Downloads\\7-240704155115-9db2c301 (8).pdf",
        "dst": "C:\\Users\\ASUS\\Downloads\\2025-05\\7-240704155115-9db2c301 (8).pdf",
        "time": "2025-10-11T15:49:06.208991",
        "dry": false
      },
      {
        "src": "C:\\Users\\ASUS\\Downloads\\7-240704155115-9db2c301 (9).pdf",
        "dst": "C:\\Users\\ASUS\\Downloads\\2025-05\\7-240704155115-9db2c301 (9).pdf",
        "time": "2025-10-11T15:49:06.209453",
        "dry": false
      },
      {
        "src": "C:\\Users\\ASUS\\Downloads\\7-240704155115-9db2c301.pdf",
        "dst": "C:\\Users\\ASUS\\Downloads\\2025-05\\7-240704155115-9db2c301.pdf",
        "time": "2025-10-11T15:49:06.209919",
        "dry": false
      },
      {
        "src": "C:\\Users\\ASUS\\Downloads\\Aap.Jaisa.Koi.2025.720p.Hindi.WEB-DL.5.1.ESub.x264-TopMovies.mkv",
        "dst": "C:\\Users\\ASUS\\Downloads\\2025-07\\Aap.Jaisa.Koi.2025.720p.Hindi.WEB-DL.5.1.ESub.x264-TopMovies.mkv",
        "time": "2025-10-11T15:49:06.210928",
        "dry": false
      },
      {
        "src": "C:\\Users\\ASUS\\Downloads\\Abu-Abu Minimalist Resume_20250226_181815_0000.pdf",
        "dst": "C:\\Users\\ASUS\\Downloads\\2025-04\\Abu-Abu Minimalist Resume_20250226_181815_0000.pdf",
        "time": "2025-10-11T15:49:06.211777",
        "dry": false
      },
      {
        "src": "C:\\Users\\ASUS\\Downloads\\age_deploy.prototxt",
        "dst": "C:\\Users\\ASUS\\Downloads\\2025-07\\age_deploy.prototxt",
        "time": "2025-10-11T15:49:06.212229",
        "dry": false
      },
      {
        "src": "C:\\Users\\ASUS\\Downloads\\age_net (1).caffemodel",
        "dst": "C:\\Users\\ASUS\\Downloads\\2025-07\\age_net (1).caffemodel",
        "time": "2025-10-11T15:49:06.212689",
        "dry": false
      },
      {
        "src": "C:\\Users\\ASUS\\Downloads\\age_net (2).caffemodel",
        "dst": "C:\\Users\\ASUS\\Downloads\\2025-07\\age_net (2).caffemodel",
        "time": "2025-10-11T15:49:06.213620",
        "dry": false
      },
      {
        "src": "C:\\Users\\ASUS\\Downloads\\age_net.caffemodel",
        "dst": "C:\\Users\\ASUS\\Downloads\\2025-07\\age_net.caffemodel",
        "time": "2025-10-11T15:49:06.214182",
        "dry": false
      },
      {
        "src": "C:\\Users\\ASUS\\Downloads\\amazon.csv.zip",
        "dst": "C:\\Users\\ASUS\\Downloads\\2025-06\\amazon.csv.zip",
        "time": "2025-10-11T15:49:06.214598",
        "dry": false
      },
      {
        "src": "C:\\Users\\ASUS\\Downloads\\Anaconda3-2024.10-1-Windows-x86_64.exe",
        "dst": "C:\\Users\\ASUS\\Downloads\\2025-03\\Anaconda3-2024.10-1-Windows-x86_64.exe",
        "time": "2025-10-11T15:49:06.215156",
        "dry": false
      },
      {
        "src": "C:\\Users\\ASUS\\Downloads\\application (1).pdf",
        "dst": "C:\\Users\\ASUS\\Downloads\\2025-07\\application (1).pdf",
        "time": "2025-10-11T15:49:06.215576",
        "dry": false
      },
      {
        "src": "C:\\Users\\ASUS\\Downloads\\application.pdf",
        "dst": "C:\\Users\\ASUS\\Downloads\\2025-07\\application.pdf",
        "time": "2025-10-11T15:49:06.215992",
        "dry": false
      },
      {
        "src": "C:\\Users\\ASUS\\Downloads\\archive (1).zip",
        "dst": "C:\\Users\\ASUS\\Downloads\\2025-07\\archive (1).zip",
        "time": "2025-10-11T15:49:06.216364",
        "dry": false
      },
      {
        "src": "C:\\Users\\ASUS\\Downloads\\aznews-master.zip",
        "dst": "C:\\Users\\ASUS\\Downloads\\2025-07\\aznews-master.zip",
        "time": "2025-10-11T15:49:06.217159",
        "dry": false
      },
      {
        "src": "C:\\Users\\ASUS\\Downloads\\Book1.xlsx",
        "dst": "C:\\Users\\ASUS\\Downloads\\2025-07\\Book1.xlsx",
        "time": "2025-10-11T15:49:06.217670",
        "dry": false
      },
      {
        "src": "C:\\Users\\ASUS\\Downloads\\callclosedelete.py",
        "dst": "C:\\Users\\ASUS\\Downloads\\2025-06\\callclosedelete.py",
        "time": "2025-10-11T15:49:06.218164",
        "dry": false
      },
      {
        "src": "C:\\Users\\ASUS\\Downloads\\callcloseinsert.py",
        "dst": "C:\\Users\\ASUS\\Downloads\\2025-06\\callcloseinsert.py",
        "time": "2025-10-11T15:49:06.219070",
        "dry": false
      },
      {
        "src": "C:\\Users\\ASUS\\Downloads\\callfeedbackdelete.py",
        "dst": "C:\\Users\\ASUS\\Downloads\\2025-06\\callfeedbackdelete.py",
        "time": "2025-10-11T15:49:06.219543",
        "dry": false
      },
      {
        "src": "C:\\Users\\ASUS\\Downloads\\callfeedbackinsert.py",
        "dst": "C:\\Users\\ASUS\\Downloads\\2025-06\\callfeedbackinsert.py",
        "time": "2025-10-11T15:49:06.219956",
        "dry": false
      },
      {
        "src": "C:\\Users\\ASUS\\Downloads\\cardetect.py",
        "dst": "C:\\Users\\ASUS\\Downloads\\2025-07\\cardetect.py",
        "time": "2025-10-11T15:49:06.220313",
        "dry": false
      },
      {
        "src": "C:\\Users\\ASUS\\Downloads\\cars.avi",
        "dst": "C:\\Users\\ASUS\\Downloads\\2025-07\\cars.avi",
        "time": "2025-10-11T15:49:06.220671",
        "dry": false
      },
      {
        "src": "C:\\Users\\ASUS\\Downloads\\carsnew.avi",
        "dst": "C:\\Users\\ASUS\\Downloads\\2025-07\\carsnew.avi",
        "time": "2025-10-11T15:49:06.221139",
        "dry": false
      },
      {
        "src": "C:\\Users\\ASUS\\Downloads\\Codsoft-Task3-Calculator-main-2.zip",
        "dst": "C:\\Users\\ASUS\\Downloads\\2025-06\\Codsoft-Task3-Calculator-main-2.zip",
        "time": "2025-10-11T15:49:06.221530",
        "dry": false
      },
      {
        "src": "C:\\Users\\ASUS\\Downloads\\Copy of Copy of Copy of Copy of Copy of RBS BA 4th Sem SOFT SKILLS.pdf_20250514_223639_0000 (1).pdf",
        "dst": "C:\\Users\\ASUS\\Downloads\\2025-05\\Copy of Copy of Copy of Copy of Copy of RBS BA 4th Sem SOFT SKILLS.pdf_20250514_223639_0000 (1).pdf",
        "time": "2025-10-11T15:49:06.221925",
        "dry": false
      },
      {
        "src": "C:\\Users\\ASUS\\Downloads\\Copy of Copy of Copy of Copy of Copy of RBS BA 4th Sem SOFT SKILLS.pdf_20250514_223639_0000 (2).pdf",
        "dst": "C:\\Users\\ASUS\\Downloads\\2025-05\\Copy of Copy of Copy of Copy of Copy of RBS BA 4th Sem SOFT SKILLS.pdf_20250514_223639_0000 (2).pdf",
        "time": "2025-10-11T15:49:06.223183",
        "dry": false
      },
      {
        "src": "C:\\Users\\ASUS\\Downloads\\Copy of Copy of Copy of Copy of Copy of RBS BA 4th Sem SOFT SKILLS.pdf_20250514_223639_0000 (3).pdf",
        "dst": "C:\\Users\\ASUS\\Downloads\\2025-05\\Copy of Copy of Copy of Copy of Copy of RBS BA 4th Sem SOFT SKILLS.pdf_20250514_223639_0000 (3).pdf",
        "time": "2025-10-11T15:49:06.223625",
        "dry": false
      },
      {
        "src": "C:\\Users\\ASUS\\Downloads\\Copy of Copy of Copy of Copy of Copy of RBS BA 4th Sem SOFT SKILLS.pdf_20250514_223639_0000.pdf",
        "dst": "C:\\Users\\ASUS\\Downloads\\2025-05\\Copy of Copy of Copy of Copy of Copy of RBS BA 4th Sem SOFT SKILLS.pdf_20250514_223639_0000.pdf",
        "time": "2025-10-11T15:49:06.224166",
        "dry": false
      },
      {
        "src": "C:\\Users\\ASUS\\Downloads\\CopyofCopyofCopyofCopyofCopyofRBSBA4thSemSOFTSKILLSpdf_20250514_223639_00001_1747397796.zip",
        "dst": "C:\\Users\\ASUS\\Downloads\\2025-05\\CopyofCopyofCopyofCopyofCopyofRBSBA4thSemSOFTSKILLSpdf_20250514_223639_00001_1747397796.zip",
        "time": "2025-10-11T15:49:06.224734",
        "dry": false
      },
      {
        "src": "C:\\Users\\ASUS\\Downloads\\coral (1).cdr",
        "dst": "C:\\Users\\ASUS\\Downloads\\2025-05\\coral (1).cdr",
        "time": "2025-10-11T15:49:06.225182",
        "dry": false
      },
      {
        "src": "C:\\Users\\ASUS\\Downloads\\coral (2).cdr",
        "dst": "C:\\Users\\ASUS\\Downloads\\2025-05\\coral (2).cdr",
        "time": "2025-10-11T15:49:06.226128",
        "dry": false
      },
      {
        "src": "C:\\Users\\ASUS\\Downloads\\coral (3).cdr",
        "dst": "C:\\Users\\ASUS\\Downloads\\2025-05\\coral (3).cdr",
        "time": "2025-10-11T15:49:06.226670",
        "dry": false
      },
      {
        "src": "C:\\Users\\ASUS\\Downloads\\coral (4) (1).pdf",
        "dst": "C:\\Users\\ASUS\\Downloads\\2025-05\\coral (4) (1).pdf",
        "time": "2025-10-11T15:49:06.227115",
        "dry": false
      },
      {
        "src": "C:\\Users\\ASUS\\Downloads\\coral (4).cdr",
        "dst": "C:\\Users\\ASUS\\Downloads\\2025-05\\coral (4).cdr",
        "time": "2025-10-11T15:49:06.227577",
        "dry": false
      },
      {
        "src": "C:\\Users\\ASUS\\Downloads\\coral (4).pdf",
        "dst": "C:\\Users\\ASUS\\Downloads\\2025-05\\coral (4).pdf",
        "time": "2025-10-11T15:49:06.228041",
        "dry": false
      },
      {
        "src": "C:\\Users\\ASUS\\Downloads\\coral.cdr",
        "dst": "C:\\Users\\ASUS\\Downloads\\2025-05\\coral.cdr",
        "time": "2025-10-11T15:49:06.228440",
        "dry": false
      },
      {
        "src": "C:\\Users\\ASUS\\Downloads\\customerinsert.py",
        "dst": "C:\\Users\\ASUS\\Downloads\\2025-06\\customerinsert.py",
        "time": "2025-10-11T15:49:06.229015",
        "dry": false
      },
      {
        "src": "C:\\Users\\ASUS\\Downloads\\dashboardbilling.cpython-312.pyc",
        "dst": "C:\\Users\\ASUS\\Downloads\\2025-05\\dashboardbilling.cpython-312.pyc",
        "time": "2025-10-11T15:49:06.229948",
        "dry": false
      },
      {
        "src": "C:\\Users\\ASUS\\Downloads\\dashboardbilling.py",
        "dst": "C:\\Users\\ASUS\\Downloads\\2025-05\\dashboardbilling.py",
        "time": "2025-10-11T15:49:06.230390",
        "dry": false
      },
      {
        "src": "C:\\Users\\ASUS\\Downloads\\Deletebilling.cpython-312.pyc",
        "dst": "C:\\Users\\ASUS\\Downloads\\2025-05\\Deletebilling.cpython-312.pyc",
        "time": "2025-10-11T15:49:06.230765",
        "dry": false
      },
      {
        "src": "C:\\Users\\ASUS\\Downloads\\Deletebilling.py",
        "dst": "C:\\Users\\ASUS\\Downloads\\2025-05\\Deletebilling.py",
        "time": "2025-10-11T15:49:06.231145",
        "dry": false
      },
      {
        "src": "C:\\Users\\ASUS\\Downloads\\delloite.pdf",
        "dst": "C:\\Users\\ASUS\\Downloads\\2025-06\\delloite.pdf",
        "time": "2025-10-11T15:49:06.231861",
        "dry": false
      },
      {
        "src": "C:\\Users\\ASUS\\Downloads\\dentcare-1.0.0.zip",
        "dst": "C:\\Users\\ASUS\\Downloads\\2025-07\\dentcare-1.0.0.zip",
        "time": "2025-10-11T15:49:06.232340",
        "dry": false
      },
      {
        "src": "C:\\Users\\ASUS\\Downloads\\desktop.ini",
        "dst": "C:\\Users\\ASUS\\Downloads\\2025-04\\desktop.ini",
        "time": "2025-10-11T15:49:06.232870",
        "dry": false
      },
      {
        "src": "C:\\Users\\ASUS\\Downloads\\details.pdf",
        "dst": "C:\\Users\\ASUS\\Downloads\\2025-07\\details.pdf",
        "time": "2025-10-11T15:49:06.233272",
        "dry": false
      },
      {
        "src": "C:\\Users\\ASUS\\Downloads\\DHAROHAR2025SINGLE (1).xlsx",
        "dst": "C:\\Users\\ASUS\\Downloads\\2025-05\\DHAROHAR2025SINGLE (1).xlsx",
        "time": "2025-10-11T15:49:06.233662",
        "dry": false
      },
      {
        "src": "C:\\Users\\ASUS\\Downloads\\DHAROHAR2025SINGLE (2).xlsx",
        "dst": "C:\\Users\\ASUS\\Downloads\\2025-05\\DHAROHAR2025SINGLE (2).xlsx",
        "time": "2025-10-11T15:49:06.234042",
        "dry": false
      },
      {
        "src": "C:\\Users\\ASUS\\Downloads\\DHAROHAR2025SINGLE (3).xlsx",
        "dst": "C:\\Users\\ASUS\\Downloads\\2025-05\\DHAROHAR2025SINGLE (3).xlsx",
        "time": "2025-10-11T15:49:06.234412",
        "dry": false
      },
      {
        "src": "C:\\Users\\ASUS\\Downloads\\DHAROHAR2025SINGLE (4).xlsx",
        "dst": "C:\\Users\\ASUS\\Downloads\\2025-05\\DHAROHAR2025SINGLE (4).xlsx",
        "time": "2025-10-11T15:49:06.234778",
        "dry": false
      },
      {
        "src": "C:\\Users\\ASUS\\Downloads\\DHAROHAR2025SINGLE (5).xlsx",
        "dst": "C:\\Users\\ASUS\\Downloads\\2025-05\\DHAROHAR2025SINGLE (5).xlsx",
        "time": "2025-10-11T15:49:06.235169",
        "dry": false
      },
      {
        "src": "C:\\Users\\ASUS\\Downloads\\DHAROHAR2025SINGLE.xlsx",
        "dst": "C:\\Users\\ASUS\\Downloads\\2025-05\\DHAROHAR2025SINGLE.xlsx",
        "time": "2025-10-11T15:49:06.235557",
        "dry": false
      },
      {
        "src": "C:\\Users\\ASUS\\Downloads\\dnYS7MBcF0.txt",
        "dst": "C:\\Users\\ASUS\\Downloads\\2025-07\\dnYS7MBcF0.txt",
        "time": "2025-10-11T15:49:06.235924",
        "dry": false
      },
      {
        "src": "C:\\Users\\ASUS\\Downloads\\DT20256928341_Application (1).pdf",
        "dst": "C:\\Users\\ASUS\\Downloads\\2025-06\\DT20256928341_Application (1).pdf",
        "time": "2025-10-11T15:49:06.236418",
        "dry": false
      },
      {
        "src": "C:\\Users\\ASUS\\Downloads\\DT20256928341_Application.pdf",
        "dst": "C:\\Users\\ASUS\\Downloads\\2025-06\\DT20256928341_Application.pdf",
        "time": "2025-10-11T15:49:06.236975",
        "dry": false
      },
      {
        "src": "C:\\Users\\ASUS\\Downloads\\findbilling.cpython-312.pyc",
        "dst": "C:\\Users\\ASUS\\Downloads\\2025-05\\findbilling.cpython-312.pyc",
        "time": "2025-10-11T15:49:06.237504",
        "dry": false
      },
      {
        "src": "C:\\Users\\ASUS\\Downloads\\findbilling.py",
        "dst": "C:\\Users\\ASUS\\Downloads\\2025-05\\findbilling.py",
        "time": "2025-10-11T15:49:06.237958",
        "dry": false
      },
      {
        "src": "C:\\Users\\ASUS\\Downloads\\font1-forever-wedding.png",
        "dst": "C:\\Users\\ASUS\\Downloads\\2025-04\\font1-forever-wedding.png",
        "time": "2025-10-11T15:49:06.238455",
        "dry": false
      },
      {
        "src": "C:\\Users\\ASUS\\Downloads\\gad.py",
        "dst": "C:\\Users\\ASUS\\Downloads\\2025-07\\gad.py",
        "time": "2025-10-11T15:49:06.238834",
        "dry": false
      },
      {
        "src": "C:\\Users\\ASUS\\Downloads\\gender_deploy.prototxt",
        "dst": "C:\\Users\\ASUS\\Downloads\\2025-07\\gender_deploy.prototxt",
        "time": "2025-10-11T15:49:06.239185",
        "dry": false
      },
      {
        "src": "C:\\Users\\ASUS\\Downloads\\gender_net (1).caffemodel",
        "dst": "C:\\Users\\ASUS\\Downloads\\2025-07\\gender_net (1).caffemodel",
        "time": "2025-10-11T15:49:06.239754",
        "dry": false
      },
      {
        "src": "C:\\Users\\ASUS\\Downloads\\gender_net (2).caffemodel",
        "dst": "C:\\Users\\ASUS\\Downloads\\2025-07\\gender_net (2).caffemodel",
        "time": "2025-10-11T15:49:06.240226",
        "dry": false
      },
      {
        "src": "C:\\Users\\ASUS\\Downloads\\gender_net.caffemodel",
        "dst": "C:\\Users\\ASUS\\Downloads\\2025-07\\gender_net.caffemodel",
        "time": "2025-10-11T15:49:06.241041",
        "dry": false
      },
      {
        "src": "C:\\Users\\ASUS\\Downloads\\girl1.jpg",
        "dst": "C:\\Users\\ASUS\\Downloads\\2025-07\\girl1.jpg",
        "time": "2025-10-11T15:49:06.241504",
        "dry": false
      },
      {
        "src": "C:\\Users\\ASUS\\Downloads\\girl2.jpg",
        "dst": "C:\\Users\\ASUS\\Downloads\\2025-07\\girl2.jpg",
        "time": "2025-10-11T15:49:06.242109",
        "dry": false
      },
      {
        "src": "C:\\Users\\ASUS\\Downloads\\GitHubDesktopSetup-x64.exe",
        "dst": "C:\\Users\\ASUS\\Downloads\\2025-07\\GitHubDesktopSetup-x64.exe",
        "time": "2025-10-11T15:49:06.242733",
        "dry": false
      },
      {
        "src": "C:\\Users\\ASUS\\Downloads\\grill (1) (1).pdf",
        "dst": "C:\\Users\\ASUS\\Downloads\\2025-04\\grill (1) (1).pdf",
        "time": "2025-10-11T15:49:06.243537",
        "dry": false
      },
      {
        "src": "C:\\Users\\ASUS\\Downloads\\grill (1).docx",
        "dst": "C:\\Users\\ASUS\\Downloads\\2025-04\\grill (1).docx",
        "time": "2025-10-11T15:49:06.244550",
        "dry": false
      },
      {
        "src": "C:\\Users\\ASUS\\Downloads\\grill (1).pdf",
        "dst": "C:\\Users\\ASUS\\Downloads\\2025-04\\grill (1).pdf",
        "time": "2025-10-11T15:49:06.245037",
        "dry": false
      },
      {
        "src": "C:\\Users\\ASUS\\Downloads\\Grill Restaurant Website.pdf",
        "dst": "C:\\Users\\ASUS\\Downloads\\2025-04\\Grill Restaurant Website.pdf",
        "time": "2025-10-11T15:49:06.245481",
        "dry": false
      },
      {
        "src": "C:\\Users\\ASUS\\Downloads\\GROUP DETAILS ( bug epic coding).xlsx",
        "dst": "C:\\Users\\ASUS\\Downloads\\2025-05\\GROUP DETAILS ( bug epic coding).xlsx",
        "time": "2025-10-11T15:49:06.245893",
        "dry": false
      },
      {
        "src": "C:\\Users\\ASUS\\Downloads\\haarcascade_car.xml",
        "dst": "C:\\Users\\ASUS\\Downloads\\2025-07\\haarcascade_car.xml",
        "time": "2025-10-11T15:49:06.246723",
        "dry": false
      },
      {
        "src": "C:\\Users\\ASUS\\Downloads\\haarcascade_eye.xml",
        "dst": "C:\\Users\\ASUS\\Downloads\\2025-07\\haarcascade_eye.xml",
        "time": "2025-10-11T15:49:06.247133",
        "dry": false
      },
      {
        "src": "C:\\Users\\ASUS\\Downloads\\haarcascade_frontalface_default.xml",
        "dst": "C:\\Users\\ASUS\\Downloads\\2025-07\\haarcascade_frontalface_default.xml",
        "time": "2025-10-11T15:49:06.247517",
        "dry": false
      },
      {
        "src": "C:\\Users\\ASUS\\Downloads\\hero_image (1).jpg",
        "dst": "C:\\Users\\ASUS\\Downloads\\2025-04\\hero_image (1).jpg",
        "time": "2025-10-11T15:49:06.247912",
        "dry": false
      },
      {
        "src": "C:\\Users\\ASUS\\Downloads\\hero_image.jpg",
        "dst": "C:\\Users\\ASUS\\Downloads\\2025-04\\hero_image.jpg",
        "time": "2025-10-11T15:49:06.248277",
        "dry": false
      },
      {
        "src": "C:\\Users\\ASUS\\Downloads\\home",
        "dst": "C:\\Users\\ASUS\\Downloads\\2025-09\\home",
        "time": "2025-10-11T15:49:06.249156",
        "dry": false
      },
      {
        "src": "C:\\Users\\ASUS\\Downloads\\Hospital ER_Data.csv",
        "dst": "C:\\Users\\ASUS\\Downloads\\2025-07\\Hospital ER_Data.csv",
        "time": "2025-10-11T15:49:06.249522",
        "dry": false
      },
      {
        "src": "C:\\Users\\ASUS\\Downloads\\index (1).html",
        "dst": "C:\\Users\\ASUS\\Downloads\\2025-06\\index (1).html",
        "time": "2025-10-11T15:49:06.249931",
        "dry": false
      },
      {
        "src": "C:\\Users\\ASUS\\Downloads\\index.html",
        "dst": "C:\\Users\\ASUS\\Downloads\\2025-06\\index.html",
        "time": "2025-10-11T15:49:06.250284",
        "dry": false
      },
      {
        "src": "C:\\Users\\ASUS\\Downloads\\JavaCodingPack-0.4.2.exe",
        "dst": "C:\\Users\\ASUS\\Downloads\\2025-06\\JavaCodingPack-0.4.2.exe",
        "time": "2025-10-11T15:49:06.250639",
        "dry": false
      },
      {
        "src": "C:\\Users\\ASUS\\Downloads\\jdk-24_windows-x64_bin.exe",
        "dst": "C:\\Users\\ASUS\\Downloads\\2025-06\\jdk-24_windows-x64_bin.exe",
        "time": "2025-10-11T15:49:06.251031",
        "dry": false
      },
      {
        "src": "C:\\Users\\ASUS\\Downloads\\Login",
        "dst": "C:\\Users\\ASUS\\Downloads\\2025-09\\Login",
        "time": "2025-10-11T15:49:06.251438",
        "dry": false
      },
      {
        "src": "C:\\Users\\ASUS\\Downloads\\Login (1)",
        "dst": "C:\\Users\\ASUS\\Downloads\\2025-09\\Login (1)",
        "time": "2025-10-11T15:49:06.251875",
        "dry": false
      },
      {
        "src": "C:\\Users\\ASUS\\Downloads\\Login (2)",
        "dst": "C:\\Users\\ASUS\\Downloads\\2025-09\\Login (2)",
        "time": "2025-10-11T15:49:06.252249",
        "dry": false
      },
      {
        "src": "C:\\Users\\ASUS\\Downloads\\Login (3)",
        "dst": "C:\\Users\\ASUS\\Downloads\\2025-09\\Login (3)",
        "time": "2025-10-11T15:49:06.252806",
        "dry": false
      },
      {
        "src": "C:\\Users\\ASUS\\Downloads\\loginpass.txt",
        "dst": "C:\\Users\\ASUS\\Downloads\\2025-06\\loginpass.txt",
        "time": "2025-10-11T15:49:06.253518",
        "dry": false
      },
      {
        "src": "C:\\Users\\ASUS\\Downloads\\login_password.py",
        "dst": "C:\\Users\\ASUS\\Downloads\\2025-05\\login_password.py",
        "time": "2025-10-11T15:49:06.254053",
        "dry": false
      },
      {
        "src": "C:\\Users\\ASUS\\Downloads\\LOWPWmxXPm.txt",
        "dst": "C:\\Users\\ASUS\\Downloads\\2025-08\\LOWPWmxXPm.txt",
        "time": "2025-10-11T15:49:06.254567",
        "dry": false
      },
      {
        "src": "C:\\Users\\ASUS\\Downloads\\Maalik.2025.1080p.V2-HDTC.Hindi.2.0.x264-TopMovies.mkv",
        "dst": "C:\\Users\\ASUS\\Downloads\\2025-07\\Maalik.2025.1080p.V2-HDTC.Hindi.2.0.x264-TopMovies.mkv",
        "time": "2025-10-11T15:49:06.255073",
        "dry": false
      },
      {
        "src": "C:\\Users\\ASUS\\Downloads\\main project service center.zip",
        "dst": "C:\\Users\\ASUS\\Downloads\\2025-06\\main project service center.zip",
        "time": "2025-10-11T15:49:06.255899",
        "dry": false
      },
      {
        "src": "C:\\Users\\ASUS\\Downloads\\Modern Minimalist CV Resume (1).pdf",
        "dst": "C:\\Users\\ASUS\\Downloads\\2025-03\\Modern Minimalist CV Resume (1).pdf",
        "time": "2025-10-11T15:49:06.256383",
        "dry": false
      },
      {
        "src": "C:\\Users\\ASUS\\Downloads\\Modern Minimalist CV Resume.pdf",
        "dst": "C:\\Users\\ASUS\\Downloads\\2025-03\\Modern Minimalist CV Resume.pdf",
        "time": "2025-10-11T15:49:06.256889",
        "dry": false
      },
      {
        "src": "C:\\Users\\ASUS\\Downloads\\mongodb-win32-x86_64-2012plus-4.2.20-signed.msi",
        "dst": "C:\\Users\\ASUS\\Downloads\\2025-06\\mongodb-win32-x86_64-2012plus-4.2.20-signed.msi",
        "time": "2025-10-11T15:49:06.257524",
        "dry": false
      },
      {
        "src": "C:\\Users\\ASUS\\Downloads\\More SQL Queries.pptx",
        "dst": "C:\\Users\\ASUS\\Downloads\\2025-04\\More SQL Queries.pptx",
        "time": "2025-10-11T15:49:06.258866",
        "dry": false
      },
      {
        "src": "C:\\Users\\ASUS\\Downloads\\MovaviScreenRecorderSetupC_W59pjo2_.exe",
        "dst": "C:\\Users\\ASUS\\Downloads\\2025-09\\MovaviScreenRecorderSetupC_W59pjo2_.exe",
        "time": "2025-10-11T15:49:06.259686",
        "dry": false
      },
      {
        "src": "C:\\Users\\ASUS\\Downloads\\movie_genre_classification_final.csv",
        "dst": "C:\\Users\\ASUS\\Downloads\\2025-06\\movie_genre_classification_final.csv",
        "time": "2025-10-11T15:49:06.260319",
        "dry": false
      },
      {
        "src": "C:\\Users\\ASUS\\Downloads\\multishop.zip",
        "dst": "C:\\Users\\ASUS\\Downloads\\2025-07\\multishop.zip",
        "time": "2025-10-11T15:49:06.260851",
        "dry": false
      },
      {
        "src": "C:\\Users\\ASUS\\Downloads\\my-cv (1).pdf",
        "dst": "C:\\Users\\ASUS\\Downloads\\2025-07\\my-cv (1).pdf",
        "time": "2025-10-11T15:49:06.261306",
        "dry": false
      },
      {
        "src": "C:\\Users\\ASUS\\Downloads\\my-cv.pdf",
        "dst": "C:\\Users\\ASUS\\Downloads\\2025-07\\my-cv.pdf",
        "time": "2025-10-11T15:49:06.261787",
        "dry": false
      },
      {
        "src": "C:\\Users\\ASUS\\Downloads\\mysql-installer-community-8.0.41.0.msi",
        "dst": "C:\\Users\\ASUS\\Downloads\\2025-03\\mysql-installer-community-8.0.41.0.msi",
        "time": "2025-10-11T15:49:06.262234",
        "dry": false
      },
      {
        "src": "C:\\Users\\ASUS\\Downloads\\mysql-installer-community-8.0.42.0.msi",
        "dst": "C:\\Users\\ASUS\\Downloads\\2025-07\\mysql-installer-community-8.0.42.0.msi",
        "time": "2025-10-11T15:49:06.262649",
        "dry": false
      },
      {
        "src": "C:\\Users\\ASUS\\Downloads\\neha.jpeg",
        "dst": "C:\\Users\\ASUS\\Downloads\\2025-06\\neha.jpeg",
        "time": "2025-10-11T15:49:06.263082",
        "dry": false
      },
      {
        "src": "C:\\Users\\ASUS\\Downloads\\New Microsoft Word Document.docx",
        "dst": "C:\\Users\\ASUS\\Downloads\\2025-03\\New Microsoft Word Document.docx",
        "time": "2025-10-11T15:49:06.263579",
        "dry": false
      },
      {
        "src": "C:\\Users\\ASUS\\Downloads\\node-v22.19.0-x64.msi",
        "dst": "C:\\Users\\ASUS\\Downloads\\2025-09\\node-v22.19.0-x64.msi",
        "time": "2025-10-11T15:49:06.264142",
        "dry": false
      },
      {
        "src": "C:\\Users\\ASUS\\Downloads\\Online Retail.xlsx",
        "dst": "C:\\Users\\ASUS\\Downloads\\2025-06\\Online Retail.xlsx",
        "time": "2025-10-11T15:49:06.264574",
        "dry": false
      },
      {
        "src": "C:\\Users\\ASUS\\Downloads\\opencv_face_detector.pbtxt",
        "dst": "C:\\Users\\ASUS\\Downloads\\2025-07\\opencv_face_detector.pbtxt",
        "time": "2025-10-11T15:49:06.265078",
        "dry": false
      },
      {
        "src": "C:\\Users\\ASUS\\Downloads\\opencv_face_detector_uint8.pb",
        "dst": "C:\\Users\\ASUS\\Downloads\\2025-07\\opencv_face_detector_uint8.pb",
        "time": "2025-10-11T15:49:06.265462",
        "dry": false
      },
      {
        "src": "C:\\Users\\ASUS\\Downloads\\OperaGXSetup (1).exe",
        "dst": "C:\\Users\\ASUS\\Downloads\\2025-03\\OperaGXSetup (1).exe",
        "time": "2025-10-11T15:49:06.265834",
        "dry": false
      },
      {
        "src": "C:\\Users\\ASUS\\Downloads\\OperaGXSetup (2).exe",
        "dst": "C:\\Users\\ASUS\\Downloads\\2025-03\\OperaGXSetup (2).exe",
        "time": "2025-10-11T15:49:06.266210",
        "dry": false
      },
      {
        "src": "C:\\Users\\ASUS\\Downloads\\OperaGXSetup (3).exe",
        "dst": "C:\\Users\\ASUS\\Downloads\\2025-07\\OperaGXSetup (3).exe",
        "time": "2025-10-11T15:49:06.266566",
        "dry": false
      },
      {
        "src": "C:\\Users\\ASUS\\Downloads\\OperaGXSetup (4).exe",
        "dst": "C:\\Users\\ASUS\\Downloads\\2025-07\\OperaGXSetup (4).exe",
        "time": "2025-10-11T15:49:06.266915",
        "dry": false
      },
      {
        "src": "C:\\Users\\ASUS\\Downloads\\OperaGXSetup (5).exe",
        "dst": "C:\\Users\\ASUS\\Downloads\\2025-09\\OperaGXSetup (5).exe",
        "time": "2025-10-11T15:49:06.267456",
        "dry": false
      },
      {
        "src": "C:\\Users\\ASUS\\Downloads\\OperaGXSetup (6).exe",
        "dst": "C:\\Users\\ASUS\\Downloads\\2025-09\\OperaGXSetup (6).exe",
        "time": "2025-10-11T15:49:06.267905",
        "dry": false
      },
      {
        "src": "C:\\Users\\ASUS\\Downloads\\OperaGXSetup.exe",
        "dst": "C:\\Users\\ASUS\\Downloads\\2025-03\\OperaGXSetup.exe",
        "time": "2025-10-11T15:49:06.268365",
        "dry": false
      },
      {
        "src": "C:\\Users\\ASUS\\Downloads\\Paatal Lok S01 E03 Hindi 720p WEB-DL ESubs [BollyFlix].mkv",
        "dst": "C:\\Users\\ASUS\\Downloads\\2025-07\\Paatal Lok S01 E03 Hindi 720p WEB-DL ESubs [BollyFlix].mkv",
        "time": "2025-10-11T15:49:06.268802",
        "dry": false
      },
      {
        "src": "C:\\Users\\ASUS\\Downloads\\Paatal Lok S01E01 Hindi 1080p WEB-DL ESubs [BollyFlix].mkv",
        "dst": "C:\\Users\\ASUS\\Downloads\\2025-07\\Paatal Lok S01E01 Hindi 1080p WEB-DL ESubs [BollyFlix].mkv",
        "time": "2025-10-11T15:49:06.269782",
        "dry": false
      },
      {
        "src": "C:\\Users\\ASUS\\Downloads\\Paatal Lok S01E02 Hindi 1080p WEB-DL ESubs [BollyFlix].mkv",
        "dst": "C:\\Users\\ASUS\\Downloads\\2025-07\\Paatal Lok S01E02 Hindi 1080p WEB-DL ESubs [BollyFlix].mkv",
        "time": "2025-10-11T15:49:06.270244",
        "dry": false
      },
      {
        "src": "C:\\Users\\ASUS\\Downloads\\Paatal Lok S01E04 Hindi 1080p WEB-DL ESubs [BollyFlix].mkv",
        "dst": "C:\\Users\\ASUS\\Downloads\\2025-07\\Paatal Lok S01E04 Hindi 1080p WEB-DL ESubs [BollyFlix].mkv",
        "time": "2025-10-11T15:49:06.270736",
        "dry": false
      },
      {
        "src": "C:\\Users\\ASUS\\Downloads\\Paatal Lok S01E05 Hindi 1080p WEB-DL ESubs [BollyFlix].mkv",
        "dst": "C:\\Users\\ASUS\\Downloads\\2025-07\\Paatal Lok S01E05 Hindi 1080p WEB-DL ESubs [BollyFlix].mkv",
        "time": "2025-10-11T15:49:06.271159",
        "dry": false
      },
      {
        "src": "C:\\Users\\ASUS\\Downloads\\Paatal Lok S01E06 Hindi 1080p WEB-DL ESubs [BollyFlix].mkv",
        "dst": "C:\\Users\\ASUS\\Downloads\\2025-07\\Paatal Lok S01E06 Hindi 1080p WEB-DL ESubs [BollyFlix].mkv",
        "time": "2025-10-11T15:49:06.271596",
        "dry": false
      },
      {
        "src": "C:\\Users\\ASUS\\Downloads\\Paatal Lok S01E07 Hindi 1080p WEB-DL ESubs [BollyFlix].mkv",
        "dst": "C:\\Users\\ASUS\\Downloads\\2025-07\\Paatal Lok S01E07 Hindi 1080p WEB-DL ESubs [BollyFlix].mkv",
        "time": "2025-10-11T15:49:06.271978",
        "dry": false
      },
      {
        "src": "C:\\Users\\ASUS\\Downloads\\Paatal Lok S01E08 Hindi 1080p WEB-DL ESubs [BollyFlix].mkv",
        "dst": "C:\\Users\\ASUS\\Downloads\\2025-07\\Paatal Lok S01E08 Hindi 1080p WEB-DL ESubs [BollyFlix].mkv",
        "time": "2025-10-11T15:49:06.272392",
        "dry": false
      },
      {
        "src": "C:\\Users\\ASUS\\Downloads\\Paatal Lok S01E09 Hindi 1080p WEB-DL ESubs [BollyFlix].mkv",
        "dst": "C:\\Users\\ASUS\\Downloads\\2025-07\\Paatal Lok S01E09 Hindi 1080p WEB-DL ESubs [BollyFlix].mkv",
        "time": "2025-10-11T15:49:06.273348",
        "dry": false
      },
      {
        "src": "C:\\Users\\ASUS\\Downloads\\Paatal Lok S02E01 Hindi 720p WEB-DL ESub [BollyFlix].mkv",
        "dst": "C:\\Users\\ASUS\\Downloads\\2025-07\\Paatal Lok S02E01 Hindi 720p WEB-DL ESub [BollyFlix].mkv",
        "time": "2025-10-11T15:49:06.274268",
        "dry": false
      },
      {
        "src": "C:\\Users\\ASUS\\Downloads\\Paatal Lok S02E02 Hindi 720p WEB-DL ESub [BollyFlix].mkv",
        "dst": "C:\\Users\\ASUS\\Downloads\\2025-07\\Paatal Lok S02E02 Hindi 720p WEB-DL ESub [BollyFlix].mkv",
        "time": "2025-10-11T15:49:06.275308",
        "dry": false
      },
      {
        "src": "C:\\Users\\ASUS\\Downloads\\Paatal Lok S02E03 Hindi 720p WEB-DL ESub [BollyFlix].mkv",
        "dst": "C:\\Users\\ASUS\\Downloads\\2025-07\\Paatal Lok S02E03 Hindi 720p WEB-DL ESub [BollyFlix].mkv",
        "time": "2025-10-11T15:49:06.275943",
        "dry": false
      },
      {
        "src": "C:\\Users\\ASUS\\Downloads\\Paatal Lok S02E04 Hindi 720p WEB-DL ESub [BollyFlix].mkv",
        "dst": "C:\\Users\\ASUS\\Downloads\\2025-07\\Paatal Lok S02E04 Hindi 720p WEB-DL ESub [BollyFlix].mkv",
        "time": "2025-10-11T15:49:06.276483",
        "dry": false
      },
      {
        "src": "C:\\Users\\ASUS\\Downloads\\Paatal Lok S02E05 Hindi 720p WEB-DL ESub [BollyFlix].mkv",
        "dst": "C:\\Users\\ASUS\\Downloads\\2025-07\\Paatal Lok S02E05 Hindi 720p WEB-DL ESub [BollyFlix].mkv",
        "time": "2025-10-11T15:49:06.276940",
        "dry": false
      },
      {
        "src": "C:\\Users\\ASUS\\Downloads\\Paatal Lok S02E06 Hindi 720p WEB-DL ESub [BollyFlix].mkv",
        "dst": "C:\\Users\\ASUS\\Downloads\\2025-07\\Paatal Lok S02E06 Hindi 720p WEB-DL ESub [BollyFlix].mkv",
        "time": "2025-10-11T15:49:06.277355",
        "dry": false
      },
      {
        "src": "C:\\Users\\ASUS\\Downloads\\Paatal Lok S02E07 Hindi 720p WEB-DL ESub [BollyFlix].mkv",
        "dst": "C:\\Users\\ASUS\\Downloads\\2025-07\\Paatal Lok S02E07 Hindi 720p WEB-DL ESub [BollyFlix].mkv",
        "time": "2025-10-11T15:49:06.278263",
        "dry": false
      },
      {
        "src": "C:\\Users\\ASUS\\Downloads\\Paatal Lok S02E08 Hindi 720p WEB-DL ESub [BollyFlix].mkv",
        "dst": "C:\\Users\\ASUS\\Downloads\\2025-07\\Paatal Lok S02E08 Hindi 720p WEB-DL ESub [BollyFlix].mkv",
        "time": "2025-10-11T15:49:06.278749",
        "dry": false
      },
      {
        "src": "C:\\Users\\ASUS\\Downloads\\Panchayat.S04.E01.1080p.Hindi.WEB-DL.5.1.ESub.x264-TopMovies.mkv",
        "dst": "C:\\Users\\ASUS\\Downloads\\2025-07\\Panchayat.S04.E01.1080p.Hindi.WEB-DL.5.1.ESub.x264-TopMovies.mkv",
        "time": "2025-10-11T15:49:06.279323",
        "dry": false
      },
      {
        "src": "C:\\Users\\ASUS\\Downloads\\Panchayat.S04.E02.1080p.Hindi.WEB-DL.5.1.ESub.x264-TopMovies.mkv",
        "dst": "C:\\Users\\ASUS\\Downloads\\2025-07\\Panchayat.S04.E02.1080p.Hindi.WEB-DL.5.1.ESub.x264-TopMovies.mkv",
        "time": "2025-10-11T15:49:06.279825",
        "dry": false
      },
      {
        "src": "C:\\Users\\ASUS\\Downloads\\Panchayat.S04.E03.1080p.Hindi.WEB-DL.5.1.ESub.x264-TopMovies.mkv",
        "dst": "C:\\Users\\ASUS\\Downloads\\2025-07\\Panchayat.S04.E03.1080p.Hindi.WEB-DL.5.1.ESub.x264-TopMovies.mkv",
        "time": "2025-10-11T15:49:06.280245",
        "dry": false
      },
      {
        "src": "C:\\Users\\ASUS\\Downloads\\Panchayat.S04.E04.1080p.Hindi.WEB-DL.5.1.ESub.x264-TopMovies.mkv",
        "dst": "C:\\Users\\ASUS\\Downloads\\2025-07\\Panchayat.S04.E04.1080p.Hindi.WEB-DL.5.1.ESub.x264-TopMovies.mkv",
        "time": "2025-10-11T15:49:06.280669",
        "dry": false
      },
      {
        "src": "C:\\Users\\ASUS\\Downloads\\Panchayat.S04.E05.1080p.Hindi.WEB-DL.5.1.ESub.x264-TopMovies.mkv",
        "dst": "C:\\Users\\ASUS\\Downloads\\2025-07\\Panchayat.S04.E05.1080p.Hindi.WEB-DL.5.1.ESub.x264-TopMovies.mkv",
        "time": "2025-10-11T15:49:06.281091",
        "dry": false
      },
      {
        "src": "C:\\Users\\ASUS\\Downloads\\Panchayat.S04.E06.1080p.Hindi.WEB-DL.5.1.ESub.x264-TopMovies.mkv",
        "dst": "C:\\Users\\ASUS\\Downloads\\2025-07\\Panchayat.S04.E06.1080p.Hindi.WEB-DL.5.1.ESub.x264-TopMovies.mkv",
        "time": "2025-10-11T15:49:06.281968",
        "dry": false
      },
      {
        "src": "C:\\Users\\ASUS\\Downloads\\Panchayat.S04.E07.1080p.Hindi.WEB-DL.5.1.ESub.x264-TopMovies (1).mkv",
        "dst": "C:\\Users\\ASUS\\Downloads\\2025-07\\Panchayat.S04.E07.1080p.Hindi.WEB-DL.5.1.ESub.x264-TopMovies (1).mkv",
        "time": "2025-10-11T15:49:06.282415",
        "dry": false
      },
      {
        "src": "C:\\Users\\ASUS\\Downloads\\Panchayat.S04.E07.1080p.Hindi.WEB-DL.5.1.ESub.x264-TopMovies.mkv",
        "dst": "C:\\Users\\ASUS\\Downloads\\2025-07\\Panchayat.S04.E07.1080p.Hindi.WEB-DL.5.1.ESub.x264-TopMovies.mkv",
        "time": "2025-10-11T15:49:06.282917",
        "dry": false
      },
      {
        "src": "C:\\Users\\ASUS\\Downloads\\Panchayat.S04.E08.1080p.Hindi.WEB-DL.5.1.ESub.x264-TopMovies.mkv",
        "dst": "C:\\Users\\ASUS\\Downloads\\2025-07\\Panchayat.S04.E08.1080p.Hindi.WEB-DL.5.1.ESub.x264-TopMovies.mkv",
        "time": "2025-10-11T15:49:06.283338",
        "dry": false
      },
      {
        "src": "C:\\Users\\ASUS\\Downloads\\productcategorydelete.py",
        "dst": "C:\\Users\\ASUS\\Downloads\\2025-05\\productcategorydelete.py",
        "time": "2025-10-11T15:49:06.283778",
        "dry": false
      },
      {
        "src": "C:\\Users\\ASUS\\Downloads\\productcategoryfind.py",
        "dst": "C:\\Users\\ASUS\\Downloads\\2025-05\\productcategoryfind.py",
        "time": "2025-10-11T15:49:06.284178",
        "dry": false
      },
      {
        "src": "C:\\Users\\ASUS\\Downloads\\productcategoryinsert.py",
        "dst": "C:\\Users\\ASUS\\Downloads\\2025-05\\productcategoryinsert.py",
        "time": "2025-10-11T15:49:06.284724",
        "dry": false
      },
      {
        "src": "C:\\Users\\ASUS\\Downloads\\productcategoryshow.py",
        "dst": "C:\\Users\\ASUS\\Downloads\\2025-05\\productcategoryshow.py",
        "time": "2025-10-11T15:49:06.285115",
        "dry": false
      },
      {
        "src": "C:\\Users\\ASUS\\Downloads\\Profile.pdf",
        "dst": "C:\\Users\\ASUS\\Downloads\\2025-05\\Profile.pdf",
        "time": "2025-10-11T15:49:06.285544",
        "dry": false
      },
      {
        "src": "C:\\Users\\ASUS\\Downloads\\project (1).zip",
        "dst": "C:\\Users\\ASUS\\Downloads\\2025-05\\project (1).zip",
        "time": "2025-10-11T15:49:06.285913",
        "dry": false
      },
      {
        "src": "C:\\Users\\ASUS\\Downloads\\project-service center (1).zip",
        "dst": "C:\\Users\\ASUS\\Downloads\\2025-06\\project-service center (1).zip",
        "time": "2025-10-11T15:49:06.286318",
        "dry": false
      },
      {
        "src": "C:\\Users\\ASUS\\Downloads\\project-service center (2).zip",
        "dst": "C:\\Users\\ASUS\\Downloads\\2025-06\\project-service center (2).zip",
        "time": "2025-10-11T15:49:06.286710",
        "dry": false
      },
      {
        "src": "C:\\Users\\ASUS\\Downloads\\project-service center (3).zip",
        "dst": "C:\\Users\\ASUS\\Downloads\\2025-06\\project-service center (3).zip",
        "time": "2025-10-11T15:49:06.287152",
        "dry": false
      },
      {
        "src": "C:\\Users\\ASUS\\Downloads\\project-service center.zip",
        "dst": "C:\\Users\\ASUS\\Downloads\\2025-06\\project-service center.zip",
        "time": "2025-10-11T15:49:06.287705",
        "dry": false
      },
      {
        "src": "C:\\Users\\ASUS\\Downloads\\project.zip",
        "dst": "C:\\Users\\ASUS\\Downloads\\2025-05\\project.zip",
        "time": "2025-10-11T15:49:06.288114",
        "dry": false
      },
      {
        "src": "C:\\Users\\ASUS\\Downloads\\python-3.13.5-amd64.exe",
        "dst": "C:\\Users\\ASUS\\Downloads\\2025-07\\python-3.13.5-amd64.exe",
        "time": "2025-10-11T15:49:06.288479",
        "dry": false
      },
      {
        "src": "C:\\Users\\ASUS\\Downloads\\python-3.13.5-embed-amd64.zip",
        "dst": "C:\\Users\\ASUS\\Downloads\\2025-07\\python-3.13.5-embed-amd64.zip",
        "time": "2025-10-11T15:49:06.288939",
        "dry": false
      },
      {
        "src": "C:\\Users\\ASUS\\Downloads\\Railway_info.csv",
        "dst": "C:\\Users\\ASUS\\Downloads\\2025-06\\Railway_info.csv",
        "time": "2025-10-11T15:49:06.289433",
        "dry": false
      },
      {
        "src": "C:\\Users\\ASUS\\Downloads\\Reasoning (1).pdf",
        "dst": "C:\\Users\\ASUS\\Downloads\\2025-07\\Reasoning (1).pdf",
        "time": "2025-10-11T15:49:06.290448",
        "dry": false
      },
      {
        "src": "C:\\Users\\ASUS\\Downloads\\Reasoning.pdf",
        "dst": "C:\\Users\\ASUS\\Downloads\\2025-06\\Reasoning.pdf",
        "time": "2025-10-11T15:49:06.290994",
        "dry": false
      },
      {
        "src": "C:\\Users\\ASUS\\Downloads\\sales_data_10_entries.xlsx",
        "dst": "C:\\Users\\ASUS\\Downloads\\2025-07\\sales_data_10_entries.xlsx",
        "time": "2025-10-11T15:49:06.291637",
        "dry": false
      },
      {
        "src": "C:\\Users\\ASUS\\Downloads\\Sales_Data_200.xlsx",
        "dst": "C:\\Users\\ASUS\\Downloads\\2025-07\\Sales_Data_200.xlsx",
        "time": "2025-10-11T15:49:06.292805",
        "dry": false
      },
      {
        "src": "C:\\Users\\ASUS\\Downloads\\savebilling (1).py",
        "dst": "C:\\Users\\ASUS\\Downloads\\2025-05\\savebilling (1).py",
        "time": "2025-10-11T15:49:06.293202",
        "dry": false
      },
      {
        "src": "C:\\Users\\ASUS\\Downloads\\savebilling.cpython-312.pyc",
        "dst": "C:\\Users\\ASUS\\Downloads\\2025-05\\savebilling.cpython-312.pyc",
        "time": "2025-10-11T15:49:06.293621",
        "dry": false
      },
      {
        "src": "C:\\Users\\ASUS\\Downloads\\savebilling.py",
        "dst": "C:\\Users\\ASUS\\Downloads\\2025-05\\savebilling.py",
        "time": "2025-10-11T15:49:06.294428",
        "dry": false
      },
      {
        "src": "C:\\Users\\ASUS\\Downloads\\script (1).js",
        "dst": "C:\\Users\\ASUS\\Downloads\\2025-07\\script (1).js",
        "time": "2025-10-11T15:49:06.294860",
        "dry": false
      },
      {
        "src": "C:\\Users\\ASUS\\Downloads\\script.js",
        "dst": "C:\\Users\\ASUS\\Downloads\\2025-06\\script.js",
        "time": "2025-10-11T15:49:06.295254",
        "dry": false
      },
      {
        "src": "C:\\Users\\ASUS\\Downloads\\seervicecenterfind.py",
        "dst": "C:\\Users\\ASUS\\Downloads\\2025-05\\seervicecenterfind.py",
        "time": "2025-10-11T15:49:06.295756",
        "dry": false
      },
      {
        "src": "C:\\Users\\ASUS\\Downloads\\servicecenter-project.txt",
        "dst": "C:\\Users\\ASUS\\Downloads\\2025-05\\servicecenter-project.txt",
        "time": "2025-10-11T15:49:06.296136",
        "dry": false
      },
      {
        "src": "C:\\Users\\ASUS\\Downloads\\servicecenterdelete.py",
        "dst": "C:\\Users\\ASUS\\Downloads\\2025-05\\servicecenterdelete.py",
        "time": "2025-10-11T15:49:06.296512",
        "dry": false
      },
      {
        "src": "C:\\Users\\ASUS\\Downloads\\servicecenterinsert.py",
        "dst": "C:\\Users\\ASUS\\Downloads\\2025-05\\servicecenterinsert.py",
        "time": "2025-10-11T15:49:06.296879",
        "dry": false
      },
      {
        "src": "C:\\Users\\ASUS\\Downloads\\servicecentershow.py",
        "dst": "C:\\Users\\ASUS\\Downloads\\2025-05\\servicecentershow.py",
        "time": "2025-10-11T15:49:06.297239",
        "dry": false
      },
      {
        "src": "C:\\Users\\ASUS\\Downloads\\sharma (1).docx",
        "dst": "C:\\Users\\ASUS\\Downloads\\2025-07\\sharma (1).docx",
        "time": "2025-10-11T15:49:06.297784",
        "dry": false
      },
      {
        "src": "C:\\Users\\ASUS\\Downloads\\sharma (3).docx",
        "dst": "C:\\Users\\ASUS\\Downloads\\2025-07\\sharma (3).docx",
        "time": "2025-10-11T15:49:06.298369",
        "dry": false
      },
      {
        "src": "C:\\Users\\ASUS\\Downloads\\sharma.docx",
        "dst": "C:\\Users\\ASUS\\Downloads\\2025-07\\sharma.docx",
        "time": "2025-10-11T15:49:06.298939",
        "dry": false
      },
      {
        "src": "C:\\Users\\ASUS\\Downloads\\showbilling.cpython-312.pyc",
        "dst": "C:\\Users\\ASUS\\Downloads\\2025-05\\showbilling.cpython-312.pyc",
        "time": "2025-10-11T15:49:06.299351",
        "dry": false
      },
      {
        "src": "C:\\Users\\ASUS\\Downloads\\showbilling.py",
        "dst": "C:\\Users\\ASUS\\Downloads\\2025-05\\showbilling.py",
        "time": "2025-10-11T15:49:06.299999",
        "dry": false
      },
      {
        "src": "C:\\Users\\ASUS\\Downloads\\Sneha sharma (1).pdf",
        "dst": "C:\\Users\\ASUS\\Downloads\\2025-07\\Sneha sharma (1).pdf",
        "time": "2025-10-11T15:49:06.300516",
        "dry": false
      },
      {
        "src": "C:\\Users\\ASUS\\Downloads\\Sneha sharma.docx",
        "dst": "C:\\Users\\ASUS\\Downloads\\2025-07\\Sneha sharma.docx",
        "time": "2025-10-11T15:49:06.301023",
        "dry": false
      },
      {
        "src": "C:\\Users\\ASUS\\Downloads\\Sneha sharma.pdf",
        "dst": "C:\\Users\\ASUS\\Downloads\\2025-06\\Sneha sharma.pdf",
        "time": "2025-10-11T15:49:06.301488",
        "dry": false
      },
      {
        "src": "C:\\Users\\ASUS\\Downloads\\sqltest (1).docx",
        "dst": "C:\\Users\\ASUS\\Downloads\\2025-04\\sqltest (1).docx",
        "time": "2025-10-11T15:49:06.301886",
        "dry": false
      },
      {
        "src": "C:\\Users\\ASUS\\Downloads\\sqltest (2).docx",
        "dst": "C:\\Users\\ASUS\\Downloads\\2025-04\\sqltest (2).docx",
        "time": "2025-10-11T15:49:06.302277",
        "dry": false
      },
      {
        "src": "C:\\Users\\ASUS\\Downloads\\sqltest (3).docx",
        "dst": "C:\\Users\\ASUS\\Downloads\\2025-04\\sqltest (3).docx",
        "time": "2025-10-11T15:49:06.302779",
        "dry": false
      },
      {
        "src": "C:\\Users\\ASUS\\Downloads\\sqltest (4).docx",
        "dst": "C:\\Users\\ASUS\\Downloads\\2025-04\\sqltest (4).docx",
        "time": "2025-10-11T15:49:06.303353",
        "dry": false
      },
      {
        "src": "C:\\Users\\ASUS\\Downloads\\sqltest (5).docx",
        "dst": "C:\\Users\\ASUS\\Downloads\\2025-04\\sqltest (5).docx",
        "time": "2025-10-11T15:49:06.304115",
        "dry": false
      },
      {
        "src": "C:\\Users\\ASUS\\Downloads\\sqltest.docx",
        "dst": "C:\\Users\\ASUS\\Downloads\\2025-04\\sqltest.docx",
        "time": "2025-10-11T15:49:06.304607",
        "dry": false
      },
      {
        "src": "C:\\Users\\ASUS\\Downloads\\style.css",
        "dst": "C:\\Users\\ASUS\\Downloads\\2025-06\\style.css",
        "time": "2025-10-11T15:49:06.305008",
        "dry": false
      },
      {
        "src": "C:\\Users\\ASUS\\Downloads\\styles (1).css",
        "dst": "C:\\Users\\ASUS\\Downloads\\2025-06\\styles (1).css",
        "time": "2025-10-11T15:49:06.305451",
        "dry": false
      },
      {
        "src": "C:\\Users\\ASUS\\Downloads\\styles-responsive.css",
        "dst": "C:\\Users\\ASUS\\Downloads\\2025-07\\styles-responsive.css",
        "time": "2025-10-11T15:49:06.305827",
        "dry": false
      },
      {
        "src": "C:\\Users\\ASUS\\Downloads\\styles.css",
        "dst": "C:\\Users\\ASUS\\Downloads\\2025-06\\styles.css",
        "time": "2025-10-11T15:49:06.306338",
        "dry": false
      },
      {
        "src": "C:\\Users\\ASUS\\Downloads\\sublime_text_build_4200_x64_setup.exe",
        "dst": "C:\\Users\\ASUS\\Downloads\\2025-07\\sublime_text_build_4200_x64_setup.exe",
        "time": "2025-10-11T15:49:06.306814",
        "dry": false
      },
      {
        "src": "C:\\Users\\ASUS\\Downloads\\synopsis MCA(I) (1).pdf",
        "dst": "C:\\Users\\ASUS\\Downloads\\2025-04\\synopsis MCA(I) (1).pdf",
        "time": "2025-10-11T15:49:06.307530",
        "dry": false
      },
      {
        "src": "C:\\Users\\ASUS\\Downloads\\synopsis MCA(I) (2) (1) (1).pdf",
        "dst": "C:\\Users\\ASUS\\Downloads\\2025-04\\synopsis MCA(I) (2) (1) (1).pdf",
        "time": "2025-10-11T15:49:06.308102",
        "dry": false
      },
      {
        "src": "C:\\Users\\ASUS\\Downloads\\synopsis MCA(I) (2) (1) (2).pdf",
        "dst": "C:\\Users\\ASUS\\Downloads\\2025-04\\synopsis MCA(I) (2) (1) (2).pdf",
        "time": "2025-10-11T15:49:06.309446",
        "dry": false
      },
      {
        "src": "C:\\Users\\ASUS\\Downloads\\synopsis MCA(I) (2) (1) (3).pdf",
        "dst": "C:\\Users\\ASUS\\Downloads\\2025-04\\synopsis MCA(I) (2) (1) (3).pdf",
        "time": "2025-10-11T15:49:06.310008",
        "dry": false
      },
      {
        "src": "C:\\Users\\ASUS\\Downloads\\synopsis MCA(I) (2) (1) (4).pdf",
        "dst": "C:\\Users\\ASUS\\Downloads\\2025-04\\synopsis MCA(I) (2) (1) (4).pdf",
        "time": "2025-10-11T15:49:06.310450",
        "dry": false
      },
      {
        "src": "C:\\Users\\ASUS\\Downloads\\synopsis MCA(I) (2) (1) (5).pdf",
        "dst": "C:\\Users\\ASUS\\Downloads\\2025-04\\synopsis MCA(I) (2) (1) (5).pdf",
        "time": "2025-10-11T15:49:06.310910",
        "dry": false
      },
      {
        "src": "C:\\Users\\ASUS\\Downloads\\synopsis MCA(I) (2) (1).pdf",
        "dst": "C:\\Users\\ASUS\\Downloads\\2025-04\\synopsis MCA(I) (2) (1).pdf",
        "time": "2025-10-11T15:49:06.311333",
        "dry": false
      },
      {
        "src": "C:\\Users\\ASUS\\Downloads\\synopsis MCA(I) (2).docx",
        "dst": "C:\\Users\\ASUS\\Downloads\\2025-04\\synopsis MCA(I) (2).docx",
        "time": "2025-10-11T15:49:06.311754",
        "dry": false
      },
      {
        "src": "C:\\Users\\ASUS\\Downloads\\synopsis MCA(I) (2).pdf",
        "dst": "C:\\Users\\ASUS\\Downloads\\2025-04\\synopsis MCA(I) (2).pdf",
        "time": "2025-10-11T15:49:06.312159",
        "dry": false
      },
      {
        "src": "C:\\Users\\ASUS\\Downloads\\synopsis MCA(I).pdf",
        "dst": "C:\\Users\\ASUS\\Downloads\\2025-04\\synopsis MCA(I).pdf",
        "time": "2025-10-11T15:49:06.312715",
        "dry": false
      },
      {
        "src": "C:\\Users\\ASUS\\Downloads\\t1 (1).pdf",
        "dst": "C:\\Users\\ASUS\\Downloads\\2025-04\\t1 (1).pdf",
        "time": "2025-10-11T15:49:06.313702",
        "dry": false
      },
      {
        "src": "C:\\Users\\ASUS\\Downloads\\t1.docx",
        "dst": "C:\\Users\\ASUS\\Downloads\\2025-04\\t1.docx",
        "time": "2025-10-11T15:49:06.314219",
        "dry": false
      },
      {
        "src": "C:\\Users\\ASUS\\Downloads\\t1.pdf",
        "dst": "C:\\Users\\ASUS\\Downloads\\2025-04\\t1.pdf",
        "time": "2025-10-11T15:49:06.314628",
        "dry": false
      },
      {
        "src": "C:\\Users\\ASUS\\Downloads\\Task 2 Guide.pdf",
        "dst": "C:\\Users\\ASUS\\Downloads\\2025-06\\Task 2 Guide.pdf",
        "time": "2025-10-11T15:49:06.315025",
        "dry": false
      },
      {
        "src": "C:\\Users\\ASUS\\Downloads\\TCS CodeVita Questions_ By CSE Study247.pdf",
        "dst": "C:\\Users\\ASUS\\Downloads\\2025-10\\TCS CodeVita Questions_ By CSE Study247.pdf",
        "time": "2025-10-11T15:49:06.315783",
        "dry": false
      },
      {
        "src": "C:\\Users\\ASUS\\Downloads\\TITLE OF MINI PROJECT SYNOPSIS[2]tanya singhal (1) (1).pdf",
        "dst": "C:\\Users\\ASUS\\Downloads\\2025-04\\TITLE OF MINI PROJECT SYNOPSIS[2]tanya singhal (1) (1).pdf",
        "time": "2025-10-11T15:49:06.316259",
        "dry": false
      },
      {
        "src": "C:\\Users\\ASUS\\Downloads\\TITLE OF MINI PROJECT SYNOPSIS[2]tanya singhal (1).docx",
        "dst": "C:\\Users\\ASUS\\Downloads\\2025-04\\TITLE OF MINI PROJECT SYNOPSIS[2]tanya singhal (1).docx",
        "time": "2025-10-11T15:49:06.316687",
        "dry": false
      },
      {
        "src": "C:\\Users\\ASUS\\Downloads\\TITLE OF MINI PROJECT SYNOPSIS[2]tanya singhal (1).pdf",
        "dst": "C:\\Users\\ASUS\\Downloads\\2025-04\\TITLE OF MINI PROJECT SYNOPSIS[2]tanya singhal (1).pdf",
        "time": "2025-10-11T15:49:06.317151",
        "dry": false
      },
      {
        "src": "C:\\Users\\ASUS\\Downloads\\Untitled1.ipynb",
        "dst": "C:\\Users\\ASUS\\Downloads\\2025-04\\Untitled1.ipynb",
        "time": "2025-10-11T15:49:06.317593",
        "dry": false
      },
      {
        "src": "C:\\Users\\ASUS\\Downloads\\vlc-media-player-3.0.21-installer.exe",
        "dst": "C:\\Users\\ASUS\\Downloads\\2025-06\\vlc-media-player-3.0.21-installer.exe",
        "time": "2025-10-11T15:49:06.318007",
        "dry": false
      },
      {
        "src": "C:\\Users\\ASUS\\Downloads\\vlc-media-player-3.0.21-installer_lXs-Dj1.exe",
        "dst": "C:\\Users\\ASUS\\Downloads\\2025-06\\vlc-media-player-3.0.21-installer_lXs-Dj1.exe",
        "time": "2025-10-11T15:49:06.318399",
        "dry": false
      },
      {
        "src": "C:\\Users\\ASUS\\Downloads\\VSCodeUserSetup-x64-1.98.2.exe",
        "dst": "C:\\Users\\ASUS\\Downloads\\2025-03\\VSCodeUserSetup-x64-1.98.2.exe",
        "time": "2025-10-11T15:49:06.318781",
        "dry": false
      },
      {
        "src": "C:\\Users\\ASUS\\Downloads\\VSCodeUserSetup-x64-1.99.3.exe",
        "dst": "C:\\Users\\ASUS\\Downloads\\2025-04\\VSCodeUserSetup-x64-1.99.3.exe",
        "time": "2025-10-11T15:49:06.319174",
        "dry": false
      },
      {
        "src": "C:\\Users\\ASUS\\Downloads\\WEB DEVELOPMENT PROJECTS (1).pdf",
        "dst": "C:\\Users\\ASUS\\Downloads\\2025-06\\WEB DEVELOPMENT PROJECTS (1).pdf",
        "time": "2025-10-11T15:49:06.319580",
        "dry": false
      },
      {
        "src": "C:\\Users\\ASUS\\Downloads\\WEB DEVELOPMENT PROJECTS.pdf",
        "dst": "C:\\Users\\ASUS\\Downloads\\2025-06\\WEB DEVELOPMENT PROJECTS.pdf",
        "time": "2025-10-11T15:49:06.320286",
        "dry": false
      },
      {
        "src": "C:\\Users\\ASUS\\Downloads\\WhatsApp Image 2025-04-10 at 20.46.33.jpeg",
        "dst": "C:\\Users\\ASUS\\Downloads\\2025-04\\WhatsApp Image 2025-04-10 at 20.46.33.jpeg",
        "time": "2025-10-11T15:49:06.320735",
        "dry": false
      },
      {
        "src": "C:\\Users\\ASUS\\Downloads\\WhatsApp Image 2025-05-23 at 00.24.14.jpeg",
        "dst": "C:\\Users\\ASUS\\Downloads\\2025-05\\WhatsApp Image 2025-05-23 at 00.24.14.jpeg",
        "time": "2025-10-11T15:49:06.321270",
        "dry": false
      },
      {
        "src": "C:\\Users\\ASUS\\Downloads\\WhatsApp Image 2025-05-23 at 00.36.42.jpeg",
        "dst": "C:\\Users\\ASUS\\Downloads\\2025-05\\WhatsApp Image 2025-05-23 at 00.36.42.jpeg",
        "time": "2025-10-11T15:49:06.321798",
        "dry": false
      },
      {
        "src": "C:\\Users\\ASUS\\Downloads\\WhatsApp Image 2025-06-23 at 22.14.35.jpeg",
        "dst": "C:\\Users\\ASUS\\Downloads\\2025-06\\WhatsApp Image 2025-06-23 at 22.14.35.jpeg",
        "time": "2025-10-11T15:49:06.322201",
        "dry": false
      },
      {
        "src": "C:\\Users\\ASUS\\Downloads\\WhatsApp Image 2025-06-28 at 19.06.44 (1).jpeg",
        "dst": "C:\\Users\\ASUS\\Downloads\\2025-06\\WhatsApp Image 2025-06-28 at 19.06.44 (1).jpeg",
        "time": "2025-10-11T15:49:06.322694",
        "dry": false
      },
      {
        "src": "C:\\Users\\ASUS\\Downloads\\WhatsApp Image 2025-06-28 at 19.06.44.jpeg",
        "dst": "C:\\Users\\ASUS\\Downloads\\2025-06\\WhatsApp Image 2025-06-28 at 19.06.44.jpeg",
        "time": "2025-10-11T15:49:06.323198",
        "dry": false
      },
      {
        "src": "C:\\Users\\ASUS\\Downloads\\WhatsApp Installer (1).exe",
        "dst": "C:\\Users\\ASUS\\Downloads\\2025-03\\WhatsApp Installer (1).exe",
        "time": "2025-10-11T15:49:06.323649",
        "dry": false
      },
      {
        "src": "C:\\Users\\ASUS\\Downloads\\WhatsApp Installer (2).exe",
        "dst": "C:\\Users\\ASUS\\Downloads\\2025-03\\WhatsApp Installer (2).exe",
        "time": "2025-10-11T15:49:06.324058",
        "dry": false
      },
      {
        "src": "C:\\Users\\ASUS\\Downloads\\WhatsApp Installer (3).exe",
        "dst": "C:\\Users\\ASUS\\Downloads\\2025-03\\WhatsApp Installer (3).exe",
        "time": "2025-10-11T15:49:06.324465",
        "dry": false
      },
      {
        "src": "C:\\Users\\ASUS\\Downloads\\WhatsApp Installer (4).exe",
        "dst": "C:\\Users\\ASUS\\Downloads\\2025-05\\WhatsApp Installer (4).exe",
        "time": "2025-10-11T15:49:06.325045",
        "dry": false
      },
      {
        "src": "C:\\Users\\ASUS\\Downloads\\WhatsApp Installer (5).exe",
        "dst": "C:\\Users\\ASUS\\Downloads\\2025-06\\WhatsApp Installer (5).exe",
        "time": "2025-10-11T15:49:06.325527",
        "dry": false
      },
      {
        "src": "C:\\Users\\ASUS\\Downloads\\WhatsApp Installer (6).exe",
        "dst": "C:\\Users\\ASUS\\Downloads\\2025-07\\WhatsApp Installer (6).exe",
        "time": "2025-10-11T15:49:06.326236",
        "dry": false
      },
      {
        "src": "C:\\Users\\ASUS\\Downloads\\WhatsApp Installer (8).exe",
        "dst": "C:\\Users\\ASUS\\Downloads\\2025-07\\WhatsApp Installer (8).exe",
        "time": "2025-10-11T15:49:06.326757",
        "dry": false
      },
      {
        "src": "C:\\Users\\ASUS\\Downloads\\WhatsApp Installer.exe",
        "dst": "C:\\Users\\ASUS\\Downloads\\2025-03\\WhatsApp Installer.exe",
        "time": "2025-10-11T15:49:06.327306",
        "dry": false
      },
      {
        "src": "C:\\Users\\ASUS\\Downloads\\WhatsApp Unknown 2025-05-23 at 00.34.49.zip",
        "dst": "C:\\Users\\ASUS\\Downloads\\2025-05\\WhatsApp Unknown 2025-05-23 at 00.34.49.zip",
        "time": "2025-10-11T15:49:06.327728",
        "dry": false
      },
      {
        "src": "C:\\Users\\ASUS\\Downloads\\WhatsApp Unknown 2025-05-23 at 00.35.46.zip",
        "dst": "C:\\Users\\ASUS\\Downloads\\2025-05\\WhatsApp Unknown 2025-05-23 at 00.35.46.zip",
        "time": "2025-10-11T15:49:06.328242",
        "dry": false
      },
      {
        "src": "C:\\Users\\ASUS\\Downloads\\whispering-signature-personal-use.regular.ttf",
        "dst": "C:\\Users\\ASUS\\Downloads\\2025-04\\whispering-signature-personal-use.regular.ttf",
        "time": "2025-10-11T15:49:06.328731",
        "dry": false
      },
      {
        "src": "C:\\Users\\ASUS\\Downloads\\woman1.jpg",
        "dst": "C:\\Users\\ASUS\\Downloads\\2025-07\\woman1.jpg",
        "time": "2025-10-11T15:49:06.329307",
        "dry": false
      }
    ]
  },
  {
    "run_time": "2025-10-21T19:03:05.200495",
    "target": "C:\\Users\\ASUS\\Desktop\\organizer",
    "moves": [
      {
        "src": "C:\\Users\\ASUS\\Desktop\\organizer\\ScreenRecorderProject1.mkv",
        "dst": "C:\\Users\\ASUS\\Desktop\\organizer\\Videos\\ScreenRecorderProject1.mkv",
        "time": "2025-10-21T19:03:05.167720",
        "dry": false
      },
      {
        "src": "C:\\Users\\ASUS\\Desktop\\organizer\\Screenshot 2025-04-03 100036.png",
        "dst": "C:\\Users\\ASUS\\Desktop\\organizer\\Images\\Screenshot 2025-04-03 100036_1.png",
        "time": "2025-10-21T19:03:05.169298",
        "dry": false
      }
    ]
  },
  {
    "run_time": "2025-10-21T19:03:43.037503",
    "target": "C:\\Users\\ASUS\\Desktop\\organizer",
    "moves": [
      {
        "src": "C:\\Users\\ASUS\\Desktop\\organizer\\images\\Screenshot 2025-04-03 100036.png",
        "dst": "C:\\Users\\ASUS\\Desktop\\organizer\\Images\\Screenshot 2025-04-03 100036_2.png",
        "time": "2025-10-21T19:03:43.007714",
        "dry": false
      },
      {
        "src": "C:\\Users\\ASUS\\Desktop\\organizer\\images\\Screenshot 2025-04-03 100036_1.png",
        "dst": "C:\\Users\\ASUS\\Desktop\\organizer\\Images\\Screenshot 2025-04-03 100036_1_1.png",
        "time": "2025-10-21T19:03:43.008999",
        "dry": false
      },
      {
        "src": "C:\\Users\\ASUS\\Desktop\\organizer\\pdf\\application.pdf",
        "dst": "C:\\Users\\ASUS\\Desktop\\organizer\\Documents\\application.pdf",
        "time": "2025-10-21T19:03:43.010508",
        "dry": false
      },
      {
        "src": "C:\\Users\\ASUS\\Desktop\\organizer\\vedio\\application.pdf",
        "dst": "C:\\Users\\ASUS\\Desktop\\organizer\\Documents\\application_1.pdf",
        "time": "2025-10-21T19:03:43.012396",
        "dry": false
      },
      {
        "src": "C:\\Users\\ASUS\\Desktop\\organizer\\vedio\\ScreenRecorderProject1.mkv",
        "dst": "C:\\Users\\ASUS\\Desktop\\organizer\\Videos\\ScreenRecorderProject1_1.mkv",
        "time": "2025-10-21T19:03:43.013583",
        "dry": false
      },
      {
        "src": "C:\\Users\\ASUS\\Desktop\\organizer\\Videos\\ScreenRecorderProject1.mkv",
        "dst": "C:\\Users\\ASUS\\Desktop\\organizer\\Videos\\ScreenRecorderProject1_2.mkv",
        "time": "2025-10-21T19:03:43.014864",
        "dry": false
      }
    ]
  },
  {
    "run_time": "2025-10-22T17:51:28.585069",
    "target": "C:\\Users\\ASUS\\Desktop\\organizer\\images",
    "moves": [
      {
        "src": "C:\\Users\\ASUS\\Desktop\\organizer\\images\\ss (2).png",
        "dst": "C:\\Users\\ASUS\\Desktop\\organizer\\images\\Images\\ss (2).png",
        "time": "2025-10-22T17:51:28.553724",
        "dry": false
      },
      {
        "src": "C:\\Users\\ASUS\\Desktop\\organizer\\images\\ss.png",
        "dst": "C:\\Users\\ASUS\\Desktop\\organizer\\images\\Images\\ss.png",
        "time": "2025-10-22T17:51:28.556804",
        "dry": false
      }
    ]
  },
  {
    "run_time": "2025-10-22T17:53:49.884871",
    "target": "C:\\Users\\ASUS\\Desktop\\organizer\\images",
    "moves": [
      {
        "src": "C:\\Users\\ASUS\\Desktop\\organizer\\images\\Screenshot 2025-09-14 225727.png",
        "dst": "C:\\Users\\ASUS\\Desktop\\organizer\\images\\Images\\Screenshot 2025-09-14 225727.png",
        "time": "2025-10-22T17:53:49.848253",
        "dry": false
      },
      {
        "src": "C:\\Users\\ASUS\\Desktop\\organizer\\images\\Screenshot 2025-09-27 231134.png",
        "dst": "C:\\Users\\ASUS\\Desktop\\organizer\\images\\Images\\Screenshot 2025-09-27 231134.png",
        "time": "2025-10-22T17:53:49.851504",
        "dry": false
      },
      {
        "src": "C:\\Users\\ASUS\\Desktop\\organizer\\images\\Screenshot 2025-10-15 234553.png",
        "dst": "C:\\Users\\ASUS\\Desktop\\organizer\\images\\Images\\Screenshot 2025-10-15 234553.png",
        "time": "2025-10-22T17:53:49.854767",
        "dry": false
      },
      {
        "src": "C:\\Users\\ASUS\\Desktop\\organizer\\images\\Screenshot 2025-10-15 234607.png",
        "dst": "C:\\Users\\ASUS\\Desktop\\organizer\\images\\Images\\Screenshot 2025-10-15 234607.png",
        "time": "2025-10-22T17:53:49.857873",
        "dry": false
      }
    ]
  },
  {
    "run_time": "2025-10-22T17:59:16.469497",
    "target": "C:\\Users\\ASUS\\Desktop\\organizer\\images",
    "moves": [
      {
        "src": "C:\\Users\\ASUS\\Desktop\\organizer\\images\\photo - Copy.png",
        "dst": "C:\\Users\\ASUS\\Desktop\\organizer\\images\\Images\\photo - Copy.png",
        "time": "2025-10-22T17:59:16.440359",
        "dry": false
      },
      {
        "src": "C:\\Users\\ASUS\\Desktop\\organizer\\images\\photo.png",
        "dst": "C:\\Users\\ASUS\\Desktop\\organizer\\images\\Images\\photo.png",
        "time": "2025-10-22T17:59:16.447991",
        "dry": false
      }
    ]
  },
  {
    "run_time": "2025-10-23T17:28:55.879963",
    "target": "C:\\Users\\ASUS\\Desktop\\organizer",
    "moves": [
      {
        "src": "C:\\Users\\ASUS\\Desktop\\organizer\\ScreenRecorderProject2.mp4",
        "dst": "C:\\Users\\ASUS\\Desktop\\organizer\\Videos\\ScreenRecorderProject2.mp4",
        "time": "2025-10-23T17:28:55.852269",
        "dry": false
      }
    ]
  },
  {
    "run_time": "2025-10-23T17:30:55.892299",
    "target": "C:\\Users\\ASUS\\Desktop\\organizer",
    "moves": [
      {
        "src": "C:\\Users\\ASUS\\Desktop\\organizer\\_DSC1517 - Copy - Copy.JPG",
        "dst": "C:\\Users\\ASUS\\Desktop\\organizer\\Images\\_DSC1517 - Copy - Copy.JPG",
        "time": "2025-10-23T17:30:55.859342",
        "dry": false
      }
    ]
  },
  {
    "run_time": "2025-10-25T18:12:55.089835",
    "target": "C:\\Users\\ASUS\\Desktop\\organizer",
    "moves": [
      {
        "src": "C:\\Users\\ASUS\\Desktop\\organizer\\cv.pdf",
        "dst": "C:\\Users\\ASUS\\Desktop\\organizer\\Documents\\cv.pdf",
        "time": "2025-10-25T18:12:55.078629",
        "dry": false
      },
      {
        "src": "C:\\Users\\ASUS\\Desktop\\organizer\\img.jpg",
        "dst": "C:\\Users\\ASUS\\Desktop\\organizer\\Images\\img.jpg",
        "time": "2025-10-25T18:12:55.079469",
        "dry": false
      },
      {
        "src": "C:\\Users\\ASUS\\Desktop\\organizer\\vc.mkv",
        "dst": "C:\\Users\\ASUS\\Desktop\\organizer\\Videos\\vc.mkv",
        "time": "2025-10-25T18:12:55.079910",
        "dry": false
      }
    ]
  },
  {
    "run_time": "2025-10-30T04:51:36.946394",
    "target": "C:\\Users\\ASUS\\Desktop\\organizer",
    "moves": [
      {
        "src": "C:\\Users\\ASUS\\Desktop\\organizer\\Screenshot 2025-10-29 221803.png",
        "dst": "C:\\Users\\ASUS\\Desktop\\organizer\\Images\\Screenshot 2025-10-29 221803.png",
        "time": "2025-10-30T04:51:36.929398",
        "dry": false
      }
    ]
  },
  {
    "run_time": "2025-10-30T04:53:47.286615",
    "target": "C:\\Users\\ASUS\\Desktop\\organizer",
    "moves": [
      {
        "src": "C:\\Users\\ASUS\\Desktop\\organizer\\Screenshot 2025-10-29 221803.png",
        "dst": "C:\\Users\\ASUS\\Desktop\\organizer\\Images\\Screenshot 2025-10-29 221803_1.png",
        "time": "2025-10-30T04:53:47.284347",
        "dry": false
      }
    ]
  },
  {
    "run_time": "2025-10-30T04:55:45.598865",
    "target": "C:\\Users\\ASUS\\Desktop\\organizer",
    "moves": [
      {
        "src": "C:\\Users\\ASUS\\Desktop\\organizer\\Screenshot 2025-10-29 210250.png",
        "dst": "C:\\Users\\ASUS\\Desktop\\organizer\\Images\\Screenshot 2025-10-29 210250.png",
        "time": "2025-10-30T04:55:45.576522",
        "dry": false
      }
    ]
  },
  {
    "run_time": "2025-10-30T04:56:45.616016",
    "target": "C:\\Users\\ASUS\\Desktop\\organizer",
    "moves": [
      {
        "src": "C:\\Users\\ASUS\\Desktop\\organizer\\Screenshot 2025-10-29 210250.png",
        "dst": "C:\\Users\\ASUS\\Desktop\\organizer\\Images\\Screenshot 2025-10-29 210250_1.png",
        "time": "2025-10-30T04:56:45.588856",
        "dry": false
      }
    ]
  }
]